{
    "bq_dataset_name": "tabular",
    "bq_table_name": "S_2010",
    "name": "S-2010",
    "path": "https://raw.githubusercontent.com/GeoDaCenter/opioid-policy-scan/main/data_final/full_tables/S_2010.csv",
    "title": "OEPS Data Aggregated by State (2010)",
    "description": "This CSV aggregates all 2010 data variables from the OEPS v2 release at the State level.",
    "schema": {
        "primaryKey": "HEROP_ID",
        "fields": [
            {
                "name": "HEROP_ID",
                "src_name": "HEROP_ID",
                "type": "string",
                "example": "040US01-2018",
                "description": "A derived unique id corresponding to the relevant geographic unit.",
                "constraints": null,
                "theme": "Geography",
                "source": null,
                "comments": "The HEROP_ID is generated as follows: Summary Level Code + \"US\" + GEOID + \u201c-\u201d + Year. In the case of State geographies, Summary Level Code is 040 and GEOID is State FP .",
                "bq_data_type": "STRING"
            },
            {
                "name": "TotPop",
                "src_name": "TotPop",
                "type": "integer",
                "example": "7294336",
                "description": "Estimated total population",
                "constraints": null,
                "theme": "Social",
                "source": "American Community Survey 2014-2018 5 Year Estimates; 2010 Decennial Census; Integrated Public Use Microdata Service National Historic Geographic Information Systems",
                "comments": "1980, 1990, and 2000 data from respective decennial censuses downloaded from IPUMS NHGIS and aggregated upwards.",
                "bq_data_type": "INTEGER"
            },
            {
                "name": "TotVetPop",
                "src_name": "TotVetPop",
                "type": "integer",
                "example": "537713",
                "description": "Total Veteran population",
                "constraints": null,
                "theme": "Social",
                "source": "American Community Survey 2014-2018 5 Year Estimates; American Community Survey 2008-2012 5-Year Estimates",
                "comments": null,
                "bq_data_type": "INTEGER"
            },
            {
                "name": "TotUnits",
                "src_name": "TotUnits",
                "type": "integer",
                "example": "3064381",
                "description": "Count of total housing units",
                "constraints": null,
                "theme": "Social",
                "source": "American Community Survey 2014-2018 5 Year Estimates; American Community Survey 2008-2012 5-Year Estimates; Social Explorer Historic Census Data on 2010 Geographies",
                "comments": "1980, 1990, and 2000 data from respective decennial censuses downloaded from Social Explorer at county level and aggregated upwards.",
                "bq_data_type": "INTEGER"
            },
            {
                "name": "WhiteP",
                "src_name": "WhiteP",
                "type": "number",
                "example": "76.03",
                "description": "Percentage of population with race identified as white alone",
                "constraints": null,
                "theme": "Social",
                "source": "American Community Survey 2014-2018 5 Year Estimates; 2010 Decennial Census; Integrated Public Use Microdata Service National Historic Geographic Information Systems",
                "comments": "1980, 1990, and 2000 data from respective decennial censuses downloaded from IPUMS NHGIS and aggregated upwards.",
                "bq_data_type": "FLOAT"
            },
            {
                "name": "BlackP",
                "src_name": "BlackP",
                "type": "number",
                "example": "3.7",
                "description": "Percentage of population with race identified as Black or African American alone",
                "constraints": null,
                "theme": "Social",
                "source": "American Community Survey 2014-2018 5 Year Estimates; 2010 Decennial Census; Integrated Public Use Microdata Service National Historic Geographic Information Systems",
                "comments": "1980, 1990, and 2000 data from respective decennial censuses downloaded from IPUMS NHGIS and aggregated upwards.",
                "bq_data_type": "FLOAT"
            },
            {
                "name": "AmIndP",
                "src_name": "AmIndP",
                "type": "number",
                "example": "1.3",
                "description": "Percentage of population with race identified as Native American or Alaska Native alone",
                "constraints": null,
                "theme": "Social",
                "source": "American Community Survey 2014-2018 5 Year Estimates; 2010 Decennial Census; Integrated Public Use Microdata Service National Historic Geographic Information Systems",
                "comments": "1980, 1990, and 2000 data from respective decennial censuses downloaded from IPUMS NHGIS and aggregated upwards.",
                "bq_data_type": "FLOAT"
            },
            {
                "name": "AsianP",
                "src_name": "AsianP",
                "type": "number",
                "example": "8.33",
                "description": "Percentage of population with race identified as Asian alone",
                "constraints": null,
                "theme": "Social",
                "source": "American Community Survey 2014-2018 5 Year Estimates; 2010 Decennial Census; Integrated Public Use Microdata Service National Historic Geographic Information Systems",
                "comments": "1980, 1990, and 2000 data from respective decennial censuses downloaded from IPUMS NHGIS and aggregated upwards.",
                "bq_data_type": "FLOAT"
            },
            {
                "name": "PacIsP",
                "src_name": "PacIsP",
                "type": "number",
                "example": "0.66",
                "description": "Percentage of population with race identified as Native Hawaiian and Other Pacific Islander alone",
                "constraints": null,
                "theme": "Social",
                "source": "American Community Survey 2014-2018 5 Year Estimates; 2010 Decennial Census; Integrated Public Use Microdata Service National Historic Geographic Information Systems",
                "comments": "1980, 1990, and 2000 data from respective decennial censuses downloaded from IPUMS NHGIS and aggregated upwards.",
                "bq_data_type": "FLOAT"
            },
            {
                "name": "OtherP",
                "src_name": "OtherP",
                "type": "number",
                "example": "9.98",
                "description": "Percentage of Population with race not mentioned in any of the options above (includes two race or more races)",
                "constraints": null,
                "theme": "Social",
                "source": "American Community Survey 2014-2018 5 Year Estimates; 2010 Decennial Census; Integrated Public Use Microdata Service National Historic Geographic Information Systems",
                "comments": "1980, 1990, and 2000 data from respective decennial censuses downloaded from IPUMS NHGIS and aggregated upwards.",
                "bq_data_type": "FLOAT"
            },
            {
                "name": "HispP",
                "src_name": "HispP",
                "type": "number",
                "example": "12.5",
                "description": "Percentage of population with ethnicity identified as of Hispanic or Latinx origin",
                "constraints": null,
                "theme": "Social",
                "source": "American Community Survey 2014-2018 5 Year Estimates; 2010 Decennial Census; Integrated Public Use Microdata Service National Historic Geographic Information Systems",
                "comments": "1980, 1990, and 2000 data from respective decennial censuses downloaded from IPUMS NHGIS and aggregated upwards.",
                "bq_data_type": "FLOAT"
            },
            {
                "name": "Age15_24P",
                "src_name": "Age15_24P",
                "type": "number",
                "example": "12.74",
                "description": "Percentage of population between ages of 15 & 24",
                "constraints": null,
                "theme": "Social",
                "source": "American Community Survey 2014-2018 5 Year Estimates; 2010 Decennial Census; Integrated Public Use Microdata Service National Historic Geographic Information Systems",
                "comments": "1980, 1990, and 2000 data from respective decennial censuses downloaded from IPUMS NHGIS and aggregated upwards.",
                "bq_data_type": "FLOAT"
            },
            {
                "name": "Und45P",
                "src_name": "Und45P",
                "type": "number",
                "example": "59.43",
                "description": "Percentage of population below 45 years of age",
                "constraints": null,
                "theme": "Social",
                "source": "American Community Survey 2014-2018 5 Year Estimates; 2010 Decennial Census; Integrated Public Use Microdata Service National Historic Geographic Information Systems",
                "comments": "1980, 1990, and 2000 data from respective decennial censuses downloaded from IPUMS NHGIS and aggregated upwards.",
                "bq_data_type": "FLOAT"
            },
            {
                "name": "Ovr65P",
                "src_name": "Ovr65P",
                "type": "number",
                "example": "14.72",
                "description": "Percentage of population over 65",
                "constraints": null,
                "theme": "Social",
                "source": "American Community Survey 2014-2018 5 Year Estimates; 2010 Decennial Census; Integrated Public Use Microdata Service National Historic Geographic Information Systems",
                "comments": "1980, 1990, and 2000 data from respective decennial censuses downloaded from IPUMS NHGIS and aggregated upwards.",
                "bq_data_type": "FLOAT"
            },
            {
                "name": "Age0_4",
                "src_name": "Age0_4",
                "type": "integer",
                "example": "453008",
                "description": "Total population between age 0-4",
                "constraints": null,
                "theme": "Social",
                "source": "American Community Survey 2014-2018 5 Year Estimates; 2010 Decennial Census; Integrated Public Use Microdata Service National Historic Geographic Information Systems",
                "comments": "1980, 1990, and 2000 data from respective decennial censuses downloaded from IPUMS NHGIS and aggregated upwards.",
                "bq_data_type": "INTEGER"
            },
            {
                "name": "Age5_14",
                "src_name": "Age5_14",
                "type": "integer",
                "example": "909873",
                "description": "Total population between age 5-14",
                "constraints": null,
                "theme": "Social",
                "source": "American Community Survey 2014-2018 5 Year Estimates; 2010 Decennial Census; Integrated Public Use Microdata Service National Historic Geographic Information Systems",
                "comments": "1980, 1990, and 2000 data from respective decennial censuses downloaded from IPUMS NHGIS and aggregated upwards.",
                "bq_data_type": "INTEGER"
            },
            {
                "name": "Age15_19",
                "src_name": "Age15_19",
                "type": "integer",
                "example": "444352",
                "description": "Total population between age 15-19",
                "constraints": null,
                "theme": "Social",
                "source": "American Community Survey 2014-2018 5 Year Estimates; 2010 Decennial Census; Integrated Public Use Microdata Service National Historic Geographic Information Systems",
                "comments": "1980, 1990, and 2000 data from respective decennial censuses downloaded from IPUMS NHGIS and aggregated upwards.",
                "bq_data_type": "INTEGER"
            },
            {
                "name": "Age20_24",
                "src_name": "Age20_24",
                "type": "integer",
                "example": "485160",
                "description": "Total population between age 20-24",
                "constraints": null,
                "theme": "Social",
                "source": "American Community Survey 2014-2018 5 Year Estimates; 2010 Decennial Census; Integrated Public Use Microdata Service National Historic Geographic Information Systems",
                "comments": "1980, 1990, and 2000 data from respective decennial censuses downloaded from IPUMS NHGIS and aggregated upwards.",
                "bq_data_type": "INTEGER"
            },
            {
                "name": "Age15_44",
                "src_name": "Age15_44",
                "type": "integer",
                "example": "2972063",
                "description": "Total population between age 15-44",
                "constraints": null,
                "theme": "Social",
                "source": "American Community Survey 2014-2018 5 Year Estimates; 2010 Decennial Census; Integrated Public Use Microdata Service National Historic Geographic Information Systems",
                "comments": "1980, 1990, and 2000 data from respective decennial censuses downloaded from IPUMS NHGIS and aggregated upwards.",
                "bq_data_type": "INTEGER"
            },
            {
                "name": "Age45_49",
                "src_name": "Age45_49",
                "type": "integer",
                "example": "467768",
                "description": "Total population between age 45-49",
                "constraints": null,
                "theme": "Social",
                "source": "American Community Survey 2014-2018 5 Year Estimates; 2010 Decennial Census; Integrated Public Use Microdata Service National Historic Geographic Information Systems",
                "comments": "1990 and 2000 data from respective decennial censuses downloaded from IPUMS NHGIS and aggregated upwards.",
                "bq_data_type": "INTEGER"
            },
            {
                "name": "Age50_54",
                "src_name": "Age50_54",
                "type": "integer",
                "example": "476486",
                "description": "Total population between age 50-54",
                "constraints": null,
                "theme": "Social",
                "source": "American Community Survey 2014-2018 5 Year Estimates; 2010 Decennial Census; Integrated Public Use Microdata Service National Historic Geographic Information Systems",
                "comments": "1990 and 2000 data from respective decennial censuses downloaded from IPUMS NHGIS and aggregated upwards.",
                "bq_data_type": "INTEGER"
            },
            {
                "name": "Age55_59",
                "src_name": "Age55_59",
                "type": "integer",
                "example": "487173",
                "description": "Total population between age 55-59",
                "constraints": null,
                "theme": "Social",
                "source": "American Community Survey 2014-2018 5 Year Estimates; 2010 Decennial Census; Integrated Public Use Microdata Service National Historic Geographic Information Systems",
                "comments": "1980, 1990, and 2000 data from respective decennial censuses downloaded from IPUMS NHGIS and aggregated upwards.",
                "bq_data_type": "INTEGER"
            },
            {
                "name": "Age60_64",
                "src_name": "Age60_64",
                "type": "integer",
                "example": "454466",
                "description": "Total population between age 60-64",
                "constraints": null,
                "theme": "Social",
                "source": "American Community Survey 2014-2018 5 Year Estimates; 2010 Decennial Census; Integrated Public Use Microdata Service National Historic Geographic Information Systems",
                "comments": "1980, 1990, and 2000 data from respective decennial censuses downloaded from IPUMS NHGIS and aggregated upwards.",
                "bq_data_type": "INTEGER"
            },
            {
                "name": "AgeOv65",
                "src_name": "AgeOv65",
                "type": "integer",
                "example": "1073499",
                "description": "Total population at or over age 65",
                "constraints": null,
                "theme": "Social",
                "source": "American Community Survey 2014-2018 5 Year Estimates; 2010 Decennial Census; Integrated Public Use Microdata Service National Historic Geographic Information Systems",
                "comments": "1980, 1990, and 2000 data from respective decennial censuses downloaded from IPUMS NHGIS and aggregated upwards.",
                "bq_data_type": "INTEGER"
            },
            {
                "name": "AgeOv18",
                "src_name": "AgeOv18",
                "type": "integer",
                "example": "5661461",
                "description": "Total population at or over age 18",
                "constraints": null,
                "theme": "Social",
                "source": "American Community Survey 2014-2018 5 Year Estimates; 2010 Decennial Census",
                "comments": null,
                "bq_data_type": "INTEGER"
            },
            {
                "name": "DisbP",
                "src_name": "DisbP",
                "type": "number",
                "example": "12.7",
                "description": "Percentage of civilian non institutionalized population with a disability",
                "constraints": null,
                "theme": "Social",
                "source": "American Community Survey 2014-2018 5 Year Estimate; American Community Survey 2008-2012 5-Year Estimates; Integrated Public Use Microdata Service National Historic Geographic Information Systems",
                "comments": "Data from 2000 Census downloaded at county level from NHGIS and aggregated upwards.",
                "bq_data_type": "FLOAT"
            },
            {
                "name": "NoHsP",
                "src_name": "NoHsP",
                "type": "number",
                "example": "8.89",
                "description": "Percentage of population 25 years and over without a high school degree",
                "constraints": null,
                "theme": "Social",
                "source": "American Community Survey 2014-2018 5 Year Estimate; American Community Survey 2008-2012 5-Year Estimates; Integrated Public Use Microdata Service National Historic Geographic Information Systems",
                "comments": "1980, 1990, and 2000 data from respective decennial censuses downloaded from IPUMS NHGIS and aggregated upwards.",
                "bq_data_type": "FLOAT"
            },
            {
                "name": "VetP",
                "src_name": "VetP",
                "type": "number",
                "example": "9.58",
                "description": "Percent of population that are veterans",
                "constraints": null,
                "theme": "Social",
                "source": "American Community Survey 2013-2017 5 Year Estimate; American Community Survey 2008-2012 5-Year Estimates",
                "comments": null,
                "bq_data_type": "FLOAT"
            },
            {
                "name": "UnempP",
                "src_name": "UnempP",
                "type": "number",
                "example": "5.3",
                "description": "The number of unemployed individuals as a percentage of the civilian labor force",
                "constraints": null,
                "theme": "Economic",
                "source": "American Community Survey 2014-2018 5 Year Estimates; American Community Survey 2008-2012 5-Year Estimates; Social Explorer Historic Census Data on 2010 Geographies",
                "comments": "1980, 1990, and 2000 data from respective decennial censuses downloaded from Social Explorer and aggregated upwards.",
                "bq_data_type": "FLOAT"
            },
            {
                "name": "PovP",
                "src_name": "PovP",
                "type": "number",
                "example": "11.5",
                "description": "Number of individuals earning below the poverty income threshold as a percentage of the total population",
                "constraints": null,
                "theme": "Economic",
                "source": "American Community Survey 2014-2018 5 Year Estimates; American Community Survey 2008-2012 5-Year Estimates; Social Explorer Historic Census Data on 2010 Geographies",
                "comments": "1980, 1990, and 2000 data from respective decennial censuses downloaded from Social Explorer and aggregated upwards.",
                "bq_data_type": "FLOAT"
            },
            {
                "name": "MedInc",
                "src_name": "MedInc",
                "type": "integer",
                "example": "34148",
                "description": "Mean income for individuals in the past 12 months (in 2018 inflation-adjusted dollars)",
                "constraints": null,
                "theme": "Economic",
                "source": "American Community Survey 2014-2018 5 Year Estimates; American Community Survey 2008-2012 5-Year Estimates",
                "comments": null,
                "bq_data_type": "INTEGER"
            },
            {
                "name": "PciE",
                "src_name": "PciE",
                "type": "integer",
                "example": "36888",
                "description": "Per capita income for individuals in the past 12 months (in 2018 inflation-adjusted dollars)",
                "constraints": null,
                "theme": "Economic",
                "source": "American Community Survey 2014-2018 5 Year Estimates; American Community Survey 2008-2012 5-Year Estimates",
                "comments": null,
                "bq_data_type": "INTEGER"
            },
            {
                "name": "GiniCoeff",
                "src_name": "GiniCoeff",
                "type": "number",
                "example": "0.46",
                "description": "Income Inequality (Gini Coefficient)",
                "constraints": null,
                "theme": "Economic",
                "source": "American Community Survey 2014-2018 5 Year Estimates; American Community Survey 2008-2012 5-Year Estimates",
                "comments": null,
                "bq_data_type": "FLOAT"
            },
            {
                "name": "VacantP",
                "src_name": "VacantP",
                "type": "number",
                "example": "8.61",
                "description": "Percentage of vacant housing units",
                "constraints": null,
                "theme": "Environment",
                "source": "American Community Survey 2014-2018 5 Year Estimates; American Community Survey 2008-2012 5-Year Estimates; Social Explorer Historic Census Data on 2010 Geographies",
                "comments": "1980, 1990, and 2000 data from respective decennial censuses downloaded from Social Explorer and aggregated upwards.",
                "bq_data_type": "FLOAT"
            }
        ]
    }
}